molcrafts_molpy-0.2.3.dist-info/licenses/LICENSE
molpy/__init__.py
molpy/version.py
molpy/adapter/__init__.py
molpy/adapter/base.py
molpy/adapter/rdkit.py
molpy/adapter/utils.py
molpy/builder/__init__.py
molpy/builder/crystal.py
molpy/builder/polymer/__init__.py
molpy/builder/polymer/connectors.py
molpy/builder/polymer/errors.py
molpy/builder/polymer/growth_kernel.py
molpy/builder/polymer/placer.py
molpy/builder/polymer/polymer_builder.py
molpy/builder/polymer/port_utils.py
molpy/builder/polymer/sequence_generator.py
molpy/builder/polymer/stochastic_generator.py
molpy/builder/polymer/system.py
molpy/builder/polymer/types.py
molpy/compute/__init__.py
molpy/compute/base.py
molpy/compute/mcd.py
molpy/compute/pmsd.py
molpy/compute/rdkit.py
molpy/compute/result.py
molpy/compute/time_series.py
molpy/core/__init__.py
molpy/core/atomistic.py
molpy/core/box.py
molpy/core/cg.py
molpy/core/config.py
molpy/core/element.py
molpy/core/entity.py
molpy/core/forcefield.py
molpy/core/frame.py
molpy/core/logger.py
molpy/core/region.py
molpy/core/script.py
molpy/core/selector.py
molpy/core/topology.py
molpy/core/trajectory.py
molpy/core/units.py
molpy/core/utils.py
molpy/core/ops/__init__.py
molpy/core/ops/geometry.py
molpy/data/__init__.py
molpy/data/__pycache__/__init__.cpython-312.pyc
molpy/data/forcefield/__init__.py
molpy/data/forcefield/oplsaa.xml
molpy/data/forcefield/tip3p.xml
molpy/data/forcefield/__pycache__/__init__.cpython-312.pyc
molpy/engine/__init__.py
molpy/engine/base.py
molpy/engine/cp2k.py
molpy/engine/lammps.py
molpy/io/__init__.py
molpy/io/readers.py
molpy/io/utils.py
molpy/io/writers.py
molpy/io/data/__init__.py
molpy/io/data/ac.py
molpy/io/data/amber.py
molpy/io/data/base.py
molpy/io/data/gro.py
molpy/io/data/h5.py
molpy/io/data/lammps.py
molpy/io/data/lammps_molecule.py
molpy/io/data/mol2.py
molpy/io/data/pdb.py
molpy/io/data/top.py
molpy/io/data/xsf.py
molpy/io/data/xyz.py
molpy/io/forcefield/__init__.py
molpy/io/forcefield/amber.py
molpy/io/forcefield/base.py
molpy/io/forcefield/lammps.py
molcrafts_molpy-0.2.3.dist-info/METADATA
molcrafts_molpy-0.2.3.dist-info/WHEEL
molcrafts_molpy-0.2.3.dist-info/top_level.txt
molcrafts_molpy-0.2.3.dist-info/RECORD
