Metadata-Version: 2.4
Name: molcrafts-molpy
Version: 0.2.3
Summary: Modern Python framework for molecular simulation and analysis
Author-email: Roy Kid <lijichen365@gmail.com>
Maintainer-email: Roy Kid <lijichen365@gmail.com>
License: BSD-3-Clause
Project-URL: Homepage, https://github.com/MolCrafts/molpy
Project-URL: Documentation, https://molcrafts.github.io/molpy
Project-URL: Repository, https://github.com/MolCrafts/molpy.git
Project-URL: Issues, https://github.com/MolCrafts/molpy/issues
Project-URL: Changelog, https://molcrafts.github.io/molpy/changelog/
Keywords: molecular-simulation,computational-chemistry,molecular-dynamics,force-fields,scientific-computing
Classifier: Development Status :: 4 - Beta
Classifier: Intended Audience :: Science/Research
Classifier: Intended Audience :: Developers
Classifier: License :: OSI Approved :: BSD License
Classifier: Operating System :: OS Independent
Classifier: Programming Language :: Python
Classifier: Programming Language :: Python :: 3
Classifier: Programming Language :: Python :: 3.12
Classifier: Programming Language :: Python :: 3 :: Only
Classifier: Programming Language :: Python :: Implementation :: CPython
Classifier: Topic :: Scientific/Engineering
Classifier: Topic :: Scientific/Engineering :: Chemistry
Classifier: Topic :: Scientific/Engineering :: Physics
Classifier: Topic :: Software Development :: Libraries :: Python Modules
Classifier: Typing :: Typed
Requires-Python: >=3.12
License-File: LICENSE
Requires-Dist: numpy>=2.0
Requires-Dist: python-igraph>=1.0.0
Requires-Dist: lark>=1.3.1
Requires-Dist: h5py>=3.0.0
Provides-Extra: dev
Requires-Dist: pytest>=6.0.0; extra == "dev"
Requires-Dist: pytest-cov>=3.0.0; extra == "dev"
Requires-Dist: pytest-mock>=3.10.0; extra == "dev"
Requires-Dist: pre-commit>=4.0.0; extra == "dev"
Provides-Extra: doc
Requires-Dist: mkdocs>=1.4.0; extra == "doc"
Requires-Dist: mkdocs-material>=9.7.0; extra == "doc"
Requires-Dist: mkdocstrings[python]>=0.24.0; extra == "doc"
Requires-Dist: mkdocs-jupyter==0.24.7; extra == "doc"
Requires-Dist: packmol; extra == "doc"
Requires-Dist: rdkit; extra == "doc"
Requires-Dist: matplotlib; extra == "doc"
Requires-Dist: scienceplots; extra == "doc"
Provides-Extra: all
Requires-Dist: molcrafts-molpy[dev,doc]; extra == "all"
Dynamic: license-file
